[
  {
    "id": "demo-btc-105k",
    "eventId": "demo-event-btc-105k",
    "slug": "btc-above-105k-may-30-2026",
    "question": "Will BTC be above $105,000 on May 30, 2026?",
    "endDate": "2026-05-30T23:59:00Z",
    "outcomes": "[\"Yes\",\"No\"]",
    "outcomePrices": "[\"0.62\",\"0.38\"]",
    "volumeNum": 152340,
    "liquidityNum": 780000
  },
  {
    "id": "demo-eth-4k",
    "eventId": "demo-event-eth-4k",
    "slug": "eth-above-4k-july-1-2026",
    "question": "Will ETH be above $4,000 on July 1, 2026?",
    "endDate": "2026-07-01T23:59:00Z",
    "outcomes": "[\"Yes\",\"No\"]",
    "outcomePrices": "[\"0.56\",\"0.44\"]",
    "volumeNum": 128540,
    "liquidityNum": 830000
  },
  {
    "id": "demo-sol-130",
    "eventId": "demo-event-sol-130",
    "slug": "sol-below-130-june-15-2026",
    "question": "Will SOL be below $130 on June 15, 2026?",
    "endDate": "2026-06-15T23:59:00Z",
    "outcomes": "[\"Yes\",\"No\"]",
    "outcomePrices": "[\"0.48\",\"0.52\"]",
    "volumeNum": 90440,
    "liquidityNum": 510000
  },
  {
    "id": "demo-eth-5k",
    "eventId": "demo-event-eth-5k",
    "slug": "eth-above-5k-may-24-2026",
    "question": "Will ETH be above $5,000 on May 24, 2026?",
    "endDate": "2026-05-24T23:59:00Z",
    "outcomes": "[\"Yes\",\"No\"]",
    "outcomePrices": "[\"0.33\",\"0.67\"]",
    "volumeNum": 24400,
    "liquidityNum": 240000
  }
]
